{
  "$schema": "https://json-schema.org/draft/2020-12/schema",
  "$id": "tenra-guardrail.external-action-review.v1",
  "title": "Guardrail external action review",
  "type": "object",
  "additionalProperties": true,
  "required": [
    "schema",
    "exportedAt",
    "sourceApp",
    "actionKind",
    "actorLabel",
    "targetLabel",
    "summary",
    "evidence",
    "recommendedDecision",
    "traceId"
  ],
  "properties": {
    "schema": {
      "const": "tenra-guardrail.external-action-review.v1",
      "type": "string"
    },
    "exportedAt": {
      "type": "string"
    },
    "sourceApp": {
      "type": "string"
    },
    "actionKind": {
      "type": "string"
    },
    "actorLabel": {
      "type": "string"
    },
    "targetLabel": {
      "type": "string"
    },
    "summary": {
      "type": "string"
    },
    "evidence": {
      "type": "array"
    },
    "recommendedDecision": {
      "type": "string"
    },
    "traceId": {
      "type": "string"
    }
  },
  "x-tenra": {
    "ownerApp": "guardrail",
    "producerApp": "source apps",
    "consumerApps": [
      "guardrail"
    ],
    "fixture": "tenra Guardrail/fixtures/handoffs/external-action-review.json",
    "correlationFields": [
      "traceId"
    ],
    "standardControls": [
      "schema badge",
      "correlation id",
      "preview payload",
      "decision templates",
      "history"
    ]
  }
}
